timeswitch/__init__.py
timeswitch/__main__.py
timeswitch-1.0.2.dist-info/licenses/LICENSE.txt
timeswitch-1.0.2.dist-info/METADATA
timeswitch-1.0.2.dist-info/WHEEL
timeswitch-1.0.2.dist-info/entry_points.txt
timeswitch-1.0.2.dist-info/top_level.txt
timeswitch-1.0.2.dist-info/RECORD
