Metadata-Version: 2.4
Name: timeswitch
Version: 1.0.2
Summary: Test date/time against a time period expressed in a simple grammar
Home-page: https://bitbucket.org/rocketboots/timeswitch/
Author: RocketBoots Pty Ltd
Author-email: support@rocketboots.com
License: MIT
Keywords: date time range period expression language
Classifier: Development Status :: 5 - Production/Stable
Classifier: Intended Audience :: Developers
Classifier: Topic :: Software Development :: Libraries :: Python Modules
Classifier: License :: OSI Approved :: MIT License
Classifier: Programming Language :: Python :: 3
Classifier: Programming Language :: Python :: 3.7
Classifier: Programming Language :: Python :: 3.8
Classifier: Programming Language :: Python :: 3.9
Classifier: Programming Language :: Python :: 3.10
Classifier: Programming Language :: Python :: 3.11
Classifier: Programming Language :: Python :: 3.12
Classifier: Programming Language :: Python :: 3.13
License-File: LICENSE.txt
Requires-Dist: pyparsing~=3.2; python_version >= "3.9"
Requires-Dist: pyparsing~=2.1; python_version < "3.9"
Requires-Dist: enum34~=1.0
Provides-Extra: test
Requires-Dist: coverage; extra == "test"
Requires-Dist: mock; extra == "test"
Requires-Dist: nose2; extra == "test"
Requires-Dist: testfixtures; extra == "test"
Dynamic: author
Dynamic: author-email
Dynamic: classifier
Dynamic: description
Dynamic: home-page
Dynamic: keywords
Dynamic: license
Dynamic: license-file
Dynamic: provides-extra
Dynamic: requires-dist
Dynamic: summary
